aiodhcpwatcher/__init__.py
aiodhcpwatcher/py.typed
aiodhcpwatcher-1.2.0.dist-info/LICENSE
aiodhcpwatcher-1.2.0.dist-info/METADATA
aiodhcpwatcher-1.2.0.dist-info/WHEEL
aiodhcpwatcher-1.2.0.dist-info/RECORD
