Metadata-Version: 2.3
Name: aiodhcpwatcher
Version: 1.2.0
Summary: Watch for DHCP packets with asyncio
License: Apache-2.0
Author: J. Nick Koston
Author-email: nick@koston.org
Requires-Python: >=3.10
Classifier: Development Status :: 2 - Pre-Alpha
Classifier: Intended Audience :: Developers
Classifier: License :: OSI Approved :: Apache Software License
Classifier: Natural Language :: English
Classifier: Operating System :: OS Independent
Classifier: Programming Language :: Python :: 3
Classifier: Programming Language :: Python :: 3.10
Classifier: Programming Language :: Python :: 3.11
Classifier: Programming Language :: Python :: 3.12
Classifier: Programming Language :: Python :: 3.13
Classifier: Topic :: Software Development :: Libraries
Requires-Dist: scapy (>=2.5.0)
Project-URL: Bug Tracker, https://github.com/bluetooth-devices/aiodhcpwatcher/issues
Project-URL: Changelog, https://github.com/bluetooth-devices/aiodhcpwatcher/blob/main/CHANGELOG.md
Project-URL: Documentation, https://aiodhcpwatcher.readthedocs.io
Project-URL: Repository, https://github.com/bluetooth-devices/aiodhcpwatcher
